aiobotstat/__init__.py
aiobotstat/api.py
aiobotstat/base.py
aiobotstat/const.py
aiobotstat/exceptions.py
aiobotstat/models/__init__.py
aiobotstat/models/base.py
aiobotstat/models/bot_info.py
aiobotstat/models/id.py
aiobotstat/models/progress.py
aiobotstat-0.1.3.dist-info/LICENSE
aiobotstat-0.1.3.dist-info/METADATA
aiobotstat-0.1.3.dist-info/WHEEL
aiobotstat-0.1.3.dist-info/top_level.txt
aiobotstat-0.1.3.dist-info/RECORD
