Metadata-Version: 2.1
Name: aiobotstat
Version: 0.1.3
Summary: Library for api.botstat.io
Home-page: https://github.com/viuipan/aiobotstat
Author-email: viuipan@gmail.com
License: MIT
Platform: UNKNOWN
License-File: LICENSE
Requires-Dist: aiohttp
Requires-Dist: pydantic
Requires-Dist: certifi
Requires-Dist: ujson
